{
  "id": "2009-11-12-are-you-gonna-be-my-girl-de-jet",
  "published_at": "2009-11-12 09:00:06 +0100",
  "title": "Are you gonna be my girl, de Jet",
  "content": "<strong>Jet</strong>, grupo australiano que apareció en 2003 con su álbum \"<strong>Get Born</strong>\", nos dejó en el mismo ciertas joyas que tener en cuenta. Para empezar, podemos comentar que este disco ha vendido más de 3 millones y medio de copias, o que cuenta con un elenco en sus influencias digno de enmarcar: <em>The Rolling Stones, Queen, AC/DC, The Beatles, Sweet, Oasis, The Who, The Kinks, The Easybeats, The Strokes y The Faces</em>; de hecho su nombre se debe a una canción de <em>Paul McCartney.</em>\r\n\r\nLa principal joya de este album es una canción que fácilmente la conocerás: \"<strong>Are you gonna be my girl</strong>\", una canción que invita, que provoca, que mueve y levanta de su sitio a cualquiera.",
  "author": {
    "name": "jesusr",
    "url": "http://www.jesusr.es",
    "gravatar_url": "https://s.gravatar.com/avatar/3627cf44a707970b4f2b493e78030448"
  },
  "comments": [
    {
      "published_at": "2009-11-12 11:08:01 +0100",
      "content": "Un día vi en directo a un grupo que literalmente destrozo esta cancion. xD Lo unico que hacian bien era el \"Are you gonna be my girl?\" .\r\n\r\nEsto ha sido patrocinado por \"experiencias derrynianas by luizcarlos\" :)",
      "author": {
        "name": "luizcarlos"
      }
    },
    {
      "published_at": "2010-05-06 23:05:21 +0200",
      "content": "Es increible la gran fuerza que te trasmite esta cancion!\r\nbrutal!!",
      "author": {
        "name": "unpalodeluz"
      }
    }
  ],
  "metadata": {
    "album": "Get born",
    "artist": "Jet",
    "artist_url": "http://www.jettheband.com/",
    "category": "Canciones",
    "song": "Are you gonna be my girl",
    "spotify_url": "https://open.spotify.com/embed/track/305WCRhhS10XUcH6AEwZk6",
    "year": "2003"
  }
}
