{
  "id": "2010-10-07-space-lord-de-monster-magnet",
  "published_at": "2010-10-07 09:00:33 +0200",
  "title": "Space Lord, de Monster Magnet",
  "content": "Hoy os traigo un grupo que para mi era desconocido hasta hace escasos meses, aunque lleva en activo desde 1989: <strong>Monster Magne</strong>t; un grupo con influencias del grunge, del garage rock y del rock psicodélico y progresivo. Liderado por el americano (de Jersey, para ser más exactos) Dave Wyndorf, han publicado siete discos de estudio entre 1989 y la actualidad, aunque ha habido épocas de receso en las cuales, bien debido a problemas con las drogas o problemas internos, el grupo no ha tenido actividad.\r\n\r\nEn cierto modo, ha sido un grupo que pese al poco conocimiento, ha alcanzado éxito y cierto apogeo en su carrera. Alrededor de 1998 publicaron un álbum llamado <strong>Powertrip</strong>, el que para mi es el mejor disco de la banda, y en el que se encuentra uno de los mejores temas: \"<strong><em>Space Lord</em><span style=\"font-weight: normal;\">\". Un tema y un disco que trató de contagiarse del ambiente decadente de la ciudad de Las Vegas; el mismo Dave Wyndorf se mudó a dicha ciudad solo para experimentar su ritmo desenfrenado y su frivolidad. </span></strong>\r\n\r\n<strong><span style=\"font-weight: normal;\">Escuchad y divertíos. </span></strong>",
  "author": {
    "name": "jesusr",
    "url": "http://www.jesusr.es",
    "gravatar_url": "https://s.gravatar.com/avatar/3627cf44a707970b4f2b493e78030448"
  },
  "comments": [
    {
      "published_at": "2010-10-07 16:00:46 +0200",
      "content": "Muy buena cancion!",
      "author": {
        "name": "liz",
        "url": "http://atlantidaliz.blogspot.com/"
      }
    }
  ],
  "metadata": {
    "album": "Powertrip",
    "artist": "Monster Magnet",
    "category": "Canciones",
    "song": "Space Lord",
    "spotify_url": "https://open.spotify.com/embed/track/3ne6tgtarLRGXs5C6CeOZf",
    "year": "1998"
  }
}
