{
  "id": "2012-06-27-ciudadanos-de-un-lugar-llamado-mundo-de-delafe-y-las-flores",
  "published_at": "2012-06-27 08:00:00 +0200",
  "title": "Ciudadanos de un lugar llamado mundo, de Delafé y las Flores",
  "content": "No, esto no es un artículo patrocinado, ni queremos hacer publicidad. Resulta que este tema pertenece a un grupo de esos que tanto gustan: veraniegos en su concepción, coloristas, luminosos.\r\n\r\n<strong>Delafé y las flores azules </strong>es un grupo nacido en el año 2004 con base en Barcelona y basándose en un estilo tan propio como sorprendente: indie pop, buenrollistas hasta el extremo, divertidos como pocos y con bases de trip hop de la mano de letras curiosas y bien equilibradas.\r\n\r\nHasta 2010 eran un grupo alternativo minoritario que no llegaba a cotas muy altas. Sin embargo, y debido a su estilo desenfadado, se hizo cargo con su tema <em><strong>\"Ciudadanos de un lugar llamado mundo\" </strong></em>de la campaña publicitaria de una importante marca de cerveza española. Y es fácil entender como consiguieron hacerse con ese trabajo al ver el videoclip y principalmente, escuchar esta canción positivista e innovadora.",
  "author": {
    "name": "jesusr",
    "url": "http://www.jesusr.es",
    "gravatar_url": "https://s.gravatar.com/avatar/3627cf44a707970b4f2b493e78030448"
  },
  "comments": [

  ],
  "metadata": {
    "album": "Ciudadanos de un lugar llamado mundo",
    "artist": "Delafé y las flores azules",
    "artist_nationality": "Spanish",
    "category": "Canciones",
    "genre": "Alternative",
    "podcast_file": "dsong.es_20120627.mp3",
    "song": "Ciudadanos de un lugar llamado mundo",
    "spotify_url": "https://open.spotify.com/embed/track/6Sv4iAMMoPUI2T5h36nmlE",
    "year": "2011"
  }
}
