{
  "id": "2014-10-09-time-after-time-de-chet-baker",
  "published_at": "2014-10-09 00:39:16 +0200",
  "title": "Time after time, de Chet Baker",
  "content": "Vuelvo clásico, lírico, con una sorpresa quebradiza.\r\n\r\nNo leáis en voz muy alta, tal vez la delicada voz de Chet Baker rompa el equilibrio y entonces qué. Porque el amor se mueve en un hilo delicado, tela de araña matutina, embrujo de hechicera novata. Y con todo, tal vez pase el tiempo y ahí prevalezcan el hilo, la telaraña y el embrujo, todos irrompibles. Llamémoslo magia. Se llama amor.\r\n\r\nTodos conocemos a Chet Baker como trompetista. Como todos los genios, no se ceñía a una disciplina. También cantaba como los ángeles, y así lo demuestra en esta versión de \"Time after time\", reinterpretada por decenas y decenas de artistas desde su composición en 1947.\r\n\r\nCuidado. Esta canción es altamente melancólica, altamente romántica y altamente ingrávida.",
  "author": {
    "name": "Brian Edward Hyde",
    "url": "",
    "gravatar_url": "https://s.gravatar.com/avatar/2f64fccdc715052a4212341e099278e3"
  },
  "comments": [

  ],
  "metadata": {
    "album": "Chet Baker Sings",
    "artist": "Chet Baker",
    "artist_nationality": "american",
    "artist_url": "http://www.chetbaker.net/",
    "category": "Canciones",
    "genre": "Vocal jazz",
    "song": "Time after time",
    "spotify_url": "https://open.spotify.com/embed/track/4m6OC8u2rC6LMFtFWsME7d",
    "year": "1956",
    "youtube_code": "yuNy5_ojif8"
  }
}
