{
  "id": "2014-01-19-bso-la-vida-de-pi",
  "published_at": "2014-01-19 10:00:00 +0100",
  "title": "BSO: La vida de Pi",
  "content": "Cuando vi esta película tuve la sensación de presenciar un cuento de hadas con un sabor agridulce al final. Ang Lee dirige este film lleno de momentos cautivadores y verdaderamente mágicos. Es curioso el tratamiento de la historia, como en un principio tienes la sensación de estar viendo un documental y como aquello de repente hace un giro de 360 grados dejándote completamente cao.\r\n\r\nLa historia aunque a grosso modo puede parecer simple tiene multitud de trasfondo y la forma en la que finalmente culmina lo convierte en una verdadera obra maestra. Mychael Danna cumple con nota su propósito en este trabajo, además en ningún momento pretende lucirse ni adquirir demasiado protagonismo. Una banda sonora muy envolvente que ayuda en todo momento a que las emociones contenidas fluyan de forma natural como si de un cuento antes de dormir se tratara. El tema principal llamado Pis Lullaby es de lo más armonioso y bello que he oído en mucho tiempo. Todo llevado al extremo de la delicadeza e impregnado de acordes orientales haciéndolo místico y bello.\r\n\r\nA mí personalmente me ha sorprendido mucho este compositor, porque aunque es un grande de entre los grandes (Truman Capote o Asesinato en 8 milímetros) nunca pensé que se desenvolvería con tanta naturalidad por una partitura que podía haberla firmado el mismísimo A. R. Rahman.",
  "author": {
    "name": "medinaman",
    "url": "",
    "gravatar_url": "https://s.gravatar.com/avatar/c0e3284ae0bbc761f3ece32ab7fbc47f"
  },
  "comments": [

  ],
  "metadata": {
    "album": "OST: Life of Pi",
    "artist": "Mychael Danna",
    "artist_nationality": "american",
    "category": "Bandas Sonoras Originales",
    "genre": "bso",
    "spotify_url": "https://open.spotify.com/embed/album/0ogV7CBV00ONXAVx4tm0gk",
    "year": "2013"
  }
}
