{
  "id": "2009-12-01-rain-of-a-thousand-years-de-flowing-tears",
  "published_at": "2009-12-01 09:00:16 +0100",
  "title": "Rain of a Thousand Years, de Flowing Tears",
  "content": "Hoy vamos a hablar de una formación relativamente desconocida para el público en general llamada <a href=\"http://www.lastfm.es/music/Flowing+Tears/+wiki\" target=\"_blank\">Flowing Tears</a>. Formada en el año 1995 en Alemania es una banda que bucea en los sonidos del metal gótico aunque también se mueve con bastante soltura en otros estilos, todo hay que decirlo.\r\n\r\nA lo largo de su historia ha sufrido grandes cambios en su composición, ocurriendo las circunstancia de que sólo uno de los miembros fundadores forman parte actualmente del grupo. Y es que a el abandono a lo largo de su historia de algunos de sus componentes hay que sumarle la muerte en un accidente de tráfico de dos de sus miembros.\r\n\r\nUn grupo que descubrí hace relativamente poco tiempo y que, aunque al principio no me gustaron demasiado, después de varias audiciones me conquistaron. La canción que hoy voy a recomendar se llama <strong>\"Rain of a Thousand Years\"</strong> de su último disco publicado hasta la fecha <strong>\"Thy Kingdom Come\" (2008)</strong>.",
  "author": {
    "name": "Jose",
    "url": "",
    "gravatar_url": "https://s.gravatar.com/avatar/7a499d70b8711d2d3b8726bfd8b430ec"
  },
  "comments": [

  ],
  "metadata": {
    "album": "Thy Kingdom Come",
    "artist": "Flowing Tears",
    "artist_url": "http://www.flowingtears.de/",
    "category": "Canciones",
    "song": "Rain of a Thousand Years",
    "spotify_url": "https://open.spotify.com/embed/track/37HtguBIovUg6qyLD8CcQ6",
    "year": "2008"
  }
}
