{
  "id": "2010-11-04-bitty-boppy-betty-de-pink-martini",
  "published_at": "2010-11-04 09:00:44 +0100",
  "title": "Bitty Boppy Betty, de Pink Martini",
  "content": "<strong>Pink Martini</strong> es un grupo de Portland que te hace viajar a esos locos años 40 ó 50 dónde Hollywood era un lugar lleno de glamour y no estaba tan mal visto como ahora, dónde el estilo pin-up predominaba y perfectamente podríamos encajar esta pieza en <em>\"¿Quién engañó a Roger Rabbit?\"</em>\r\n\r\nEste grupo hace levantar a más de uno el ánimo por la positividad que transmite la frescura de sus canciones y la versatilidad de estilos (desde jazz hasta música latina). Cabe destacar que en un mismo disco te puede cantar en italiano, español, inglés o incluso japonés.\r\n\r\nLa canción tal y como dije arriba se encaja a la típica trama de los años 40 y 50 y hace que te olvides de lo mal que has podido llevar el día y sumergirte en esa elegancia característica de mitad del siglo XX.",
  "author": {
    "name": "dori_nami"
  },
  "comments": [
    {
      "published_at": "2010-11-04 14:42:36 +0100",
      "content": "me encanto el estilo! .D",
      "author": {
        "name": "liz",
        "url": "http://atlantidaliz.blogspot.com"
      }
    }
  ],
  "metadata": {
    "album": "Splendor in the Grass",
    "artist": "Pink Martini",
    "artist_url": "http://pinkmartini.com/",
    "category": "Canciones",
    "lector": "dori_nami",
    "song": "Bitty Boppy Betty",
    "spotify_url": "https://open.spotify.com/embed/track/5skPpj3VIqHAGkNNSkBOFl",
    "year": "2009"
  }
}
